lg3k/__init__.py
lg3k/main.py
lg3k/modules/__init__.py
lg3k/modules/api.py
lg3k/modules/database.py
lg3k/modules/firewall.py
lg3k/modules/nas.py
lg3k/modules/network.py
lg3k/modules/os.py
lg3k/modules/printer.py
lg3k/modules/smarthome.py
lg3k/modules/web_server.py
lg3k/utils/__init__.py
lg3k/utils/config.py
lg3k/utils/progress.py
lg3k/utils/timestamp.py
lg3k-0.7.0.dist-info/LICENSE
lg3k-0.7.0.dist-info/METADATA
lg3k-0.7.0.dist-info/WHEEL
lg3k-0.7.0.dist-info/entry_points.txt
lg3k-0.7.0.dist-info/top_level.txt
lg3k-0.7.0.dist-info/RECORD
