Metadata-Version: 2.1
Name: lg3k
Version: 0.7.0
Summary: Log Generator 3000 - A modular log generation tool
Home-page: https://github.com/mikl0s/LG3K
Author: Mikkel Georgsen
Author-email: lg3k@dataloes.dk
Keywords: log generator testing development monitoring
Classifier: Development Status :: 4 - Beta
Classifier: Environment :: Console
Classifier: Intended Audience :: Developers
Classifier: Intended Audience :: System Administrators
Classifier: License :: OSI Approved :: MIT License
Classifier: Operating System :: OS Independent
Classifier: Programming Language :: Python :: 3
Classifier: Programming Language :: Python :: 3.12
Classifier: Topic :: Software Development :: Testing
Classifier: Topic :: System :: Logging
Classifier: Topic :: System :: Systems Administration
Requires-Python: >=3.12
License-File: LICENSE
Requires-Dist: click>=8.0.0
Requires-Dist: rich>=10.0.0
